[
  {
    "reviewID": 9330,
    "rating": 4,
    "message": "Кошки не боялись спокойно стояли не было никаких громких шумов которые могли бы напугать их",
    "name": "Надежда",
    "avatar": "",
    "data": "2 месяца назад"
  },
  {
    "reviewID": 8801,
    "rating": 5,
    "message": "Спасибо от нас и нашего котика  за оказанную услугу! Не в первый раз обращаюсь к данному мастеру, результат всегда приятно радует, обязательно придём ещё. Мастер своего дела 💕",
    "name": "Владимир Березин",
    "avatar": "",
    "data": "3 месяца назад"
  },
  {
    "reviewID": 8305,
    "rating": 5,
    "message": "Давно ходим к Кристине,  очень нравится как делает стрижку нашей собачке,  всегда остаюсь довольной + приемлемые цены, Йорк всегда \r\nспокойной себя ведёт \r\nБудем и дальше ходить только к нашему грумеру )))",
    "name": "Алина Махмутова",
    "avatar": "https://bb-avatar.storage.yandexcloud.net/users/ec/79/ec7939a5a93a34652503bd71923edb859540316/ec7939a5a93a34652503bd71923edb859540316_200x200.jpg",
    "data": "3 месяца назад"
  },
  {
    "reviewID": 8164,
    "rating": 5,
    "message": "Спасибо большое Кристине, за терпение и умение найти подход к Биму, сделала нам красоту, не смотря на то, что Бим ни минуты не мог постоять спокойно. Мастер своего дела, очень рекомендую Кристину.",
    "name": "Елена Зотова-Гращенко",
    "avatar": "https://bb-avatar.storage.yandexcloud.net/users/fa/d4/fad470a79c337c46e0fe85ba63c0ed287859172/fad470a79c337c46e0fe85ba63c0ed287859172_200x200.jpg",
    "data": "4 месяца назад"
  },
  {
    "reviewID": 8142,
    "rating": 5,
    "message": "Большое спасибо! Обращаемся уже не в первый раз с очень характерным парнем-лабрадором. К нему всегда находится индивидуальный подход вне зависимости от «радуги» его настроения😂",
    "name": "Лина",
    "avatar": "",
    "data": "4 месяца назад"
  },
  {
    "reviewID": 8072,
    "rating": 5,
    "message": "Огромное спасибо Кристине! Всё прошло замечательно. Привозила своего красавчика в первый раз на стрижку, переживала как всё пройдет. Осталась очень довольна , Кристина с первой минуту нашла подход , сразу видно девушка очень любит то чем занимается ☺️ однозначно рекомендую)",
    "name": "Анастасия",
    "avatar": "",
    "data": "4 месяца назад"
  },
  {
    "reviewID": 8070,
    "rating": 5,
    "message": "Вам спасибо большое! Процедура прошла отлично! Не смотря на то что Миша был, как акробат все прошло идеально, ВЫ ПРОФЕССИОНАЛ СВОЕГО ДЕЛА! Придем обязательно ещё раз 🫶🏼🫶🏼🫶🏼🫶🏼",
    "name": "Алёна Кылосова",
    "avatar": "https://bb-avatar.storage.yandexcloud.net/users/05/23/05234c5cf0e814517ade92ab762511a68038887/05234c5cf0e814517ade92ab762511a68038887_200x200.jpg",
    "data": "4 месяца назад"
  },
  {
    "reviewID": 8039,
    "rating": 5,
    "message": "В очередной раз получили эстетическое удовольствие после обслуживания своих питомцев у Кристины. Очень добрый, терпеливый, с безупречным чувством красоты и меры мастер. Хочется отметить, что  со  скурпулезной точностью Кристина всегда выполняет пожелания клиента. Благодарим за работу и обязательно будем посещать Ваш салон.",
    "name": "Ленок",
    "avatar": "",
    "data": "4 месяца назад"
  },
  {
    "reviewID": 7910,
    "rating": 5,
    "message": "Были на процедуре супер-линька для лабрадора, наш непоседа,по словам Крис, вел себя очень даже достойно,спокойно доверился ее золотым ручкам ✨После процедуры заметили как шерсть на одежде практически не остается, нежели чем было до,поэтому смело записывайтесь на процедуры,Кристина лучшая в этом деле🩵",
    "name": "Елизавета",
    "avatar": "",
    "data": "4 месяца назад"
  },
  {
    "reviewID": 7809,
    "rating": 5,
    "message": "Добрый день! Я участвовала в розыгрыше у Кристины и стала победителем 🏆 Вообще у меня две собаки, и я надеялась, что удача хоть для одной из них улыбнется! Так и случилось!  1 место - полный комплекс груминга ❤️\r\nХочу сказать, мы пользовались услугами груминга и ранее, именно у Кристины. Спасибо вам за прекрасную работу и внимательное отношение к моим любимцам. Вы превосходный мастер! Рекомендую всем двумя руками 🙌",
    "name": "Марина",
    "avatar": "",
    "data": "4 месяца назад"
  },
  {
    "reviewID": 7646,
    "rating": 5,
    "message": "Все прошло замечательно! Видно, что Кристина любит животных, мой кот после стрессовой поездки в переноске сразу успокоился у нее на руках. Ушли довольные, обязательно вернемся",
    "name": "Екатерина",
    "avatar": "",
    "data": "4 месяца назад"
  },
  {
    "reviewID": 7421,
    "rating": 5,
    "message": "Пришли в первый раз, милая и приятная девушка нас встретила, справилась с нашим котом на отлично👍 всё для него прошло без стресса и дискомфорта, за что мы очень признательны и боагодарны)) Кристина, вы отличный мастер своего дела, обязательно придём к вам ещё)))",
    "name": "Алиса",
    "avatar": "",
    "data": "4 месяца назад"
  },
  {
    "reviewID": 7315,
    "rating": 5,
    "message": "Пришли в первый раз целой бандой собакенов.Обрезка коготочков прошла отлично.По нашей просьбе еще и жопку подстригли нашему чихуахуенышу.Большое спасибо!!!!Все довольны!!!Теперь только к Кристине!!!",
    "name": "Вита",
    "avatar": "",
    "data": "5 месяцев назад"
  },
  {
    "reviewID": 7236,
    "rating": 5,
    "message": "Благодарю за качественную стрижку четырёх котов, услуга оказана быстро и качественно.",
    "name": "Наталья Шибаева",
    "avatar": "",
    "data": "5 месяцев назад"
  },
  {
    "reviewID": 6390,
    "rating": 5,
    "message": "Добрый вечер,спасибо большое за проделанную работу на двумя животинками🥹\r\nПриятно всё-мастер, студия и оказанные услуги, обязательно вернемся вновь🐈🫶🏻",
    "name": "Вероника",
    "avatar": "",
    "data": "6 месяцев назад"
  },
  {
    "reviewID": 6225,
    "rating": 5,
    "message": "Добрый день!Были у грумера впервой)Нашему пёселю понравилось,остался с удовольствием и забрали довольного.Все сделано идеально,блестел от чистоты как никогда 😁не можем нарадоваться отсутствием шерсти на полу!!!Теперь будем водить только к Кристине,спасибо Вам огромное🌸",
    "name": "Ольга",
    "avatar": "",
    "data": "6 месяцев назад"
  },
  {
    "reviewID": 5919,
    "rating": 5,
    "message": "Добрый день! Кристина- мастер своего дела, а животные -это ее душа!❤️ \r\nОтдавая своего верного друга, точно знаем , что он в надежных руках!🐶 \r\nИ хочу поздравить с открытием своей студии, там очень уютно🦋\r\nЖелаю побольше мохнатых, благодарных клиентов 🐶🐈",
    "name": "Ирина",
    "avatar": "",
    "data": "6 месяцев назад"
  },
  {
    "reviewID": 5874,
    "rating": 5,
    "message": "Буся  в восторге от заботы и профессионализма Кристины)\r\nХодим уже 2 года только к Кристине)",
    "name": "Яна",
    "avatar": "",
    "data": "6 месяцев назад"
  },
  {
    "reviewID": 5853,
    "rating": 5,
    "message": "Спасибо огромное Кристине за любовь и внимательное отношение :)\r\nнашу Бонечку после посещения посто не узнать!\r\nкто куда. а мы только к Кристине за чистой и красивой шерсткой нашей любимки",
    "name": "Наталья",
    "avatar": "",
    "data": "6 месяцев назад"
  },
  {
    "reviewID": 5842,
    "rating": 5,
    "message": "Доброго дня ☀️. \r\nБыли у Кристины в прошлом году, делали весь комплекс 🐶 и решили, это наш мастер ✂️ . Были второй раз 4 января 2024г. Со спокойной душой оставляю Габи на спа и занимаюсь своими делами. Это про доверие 🙏. Осуждаем с Кристиной, что делаем и получаем красивую Габи.Это про профессионализм. \r\nБлагодарю за подарки-фото, парфюм, вкусняшки. Это про любовь своего хобби, работы. \r\nКристина, спасибо за ваш труд, вы делаете нас красивыми ( т.е. Габи 🐶). ♥️♥️♥️",
    "name": "Светлана",
    "avatar": "",
    "data": "7 месяцев назад"
  },
  {
    "reviewID": 5716,
    "rating": 5,
    "message": "Кристина, любимый и единственный грумер 🤍🤍🤍 наш  мальчишка счастлив, ухожен и красив, а значит счастливы мы. Спасибо 🤍🤍🤍",
    "name": "Елена",
    "avatar": "",
    "data": "7 месяцев назад"
  },
  {
    "reviewID": 5355,
    "rating": 5,
    "message": "Прекрасный мастер\r\nНаша кошка чувствует себя комфортно, результат работы - шикарный \r\nКошка красивая, с короткими коготками за приемлемый прайс 💪🏻💪🏻👍👍",
    "name": "Имануил",
    "avatar": "",
    "data": "7 месяцев назад"
  },
  {
    "reviewID": 5334,
    "rating": 5,
    "message": "Подстригли супер,спасибо за такую красоту!!!Будем к вам ходить)",
    "name": "Татьяна",
    "avatar": "",
    "data": "7 месяцев назад"
  },
  {
    "reviewID": 5297,
    "rating": 5,
    "message": "С тех пор как попали к Кристине  стрижемся только у неё. \r\nОна мастер своего дела !\r\nОбладает удивительным даром видения, ей не надо говорить как стрич вашего питомца она его сама сделает неотразимым .\r\nСпасибо Кристиночка за красоту !!!!",
    "name": "Алёна",
    "avatar": "",
    "data": "7 месяцев назад"
  },
  {
    "reviewID": 4532,
    "rating": 5,
    "message": "Кристина Вы космос ✨\r\nМы теперь толко к Вам! 🦊🥰",
    "name": "Александра",
    "avatar": "",
    "data": "7 месяцев назад"
  },
  {
    "reviewID": 4363,
    "rating": 5,
    "message": "Хочу поделится впечатлениями о работе мастера с большой буквы , ходим уже не первый год ,не каких нареканий, Кристина просто человек с большущим сердцем! Иначе не объяснить ее любовь  к хвостикам 🐶\r\nХочется пожелать процветания и достижение всего задуманного❤️",
    "name": "Ольга",
    "avatar": "",
    "data": "9 месяцев назад"
  },
  {
    "reviewID": 3206,
    "rating": 5,
    "message": "Всё прекрасно, как и всегда. Наш мальчишка в надежных руках. Кристина очень добрая, внимательная, ответственная и аккуратная. Всегда получаем обратную связь, видим как проводятся процедуры гигиены нашего мальчугана. Посещаем грумера ежемесячно, последние 5 месяцев стрижки, укладки, только у Кристины. Рекомендуем. Отличный мастер.",
    "name": "Елена",
    "avatar": "",
    "data": "11 месяцев назад"
  },
  {
    "reviewID": 2777,
    "rating": 5,
    "message": "Уже полгода ходим к Кристине😇 Очень хороший, доброжелательный и аккуратный мастер. Каким-то образом всегда находит подход к моей манипуляторше) После каждого посещения уходим только с положительными эмоциями. Огромное спасибо!💜",
    "name": "Кари",
    "avatar": "",
    "data": "1 год назад"
  },
  {
    "reviewID": 2751,
    "rating": 5,
    "message": "Уже 2 раза ходили к Кристине на груминг корги. Все прошло замечательно,  собака довольна и я тоже🤗 Спасибо за профессионализм",
    "name": "Анна",
    "avatar": "",
    "data": "1 год назад"
  }
]